serviceboot/__init__.py
serviceboot/build_docker.py
serviceboot/build_zip.py
serviceboot/command.py
serviceboot/compile_python.py
serviceboot/consul_client.py
serviceboot/oauth_client.py
serviceboot/onboarding.py
serviceboot/request_info.py
serviceboot/serviceboot.py
serviceboot/token_service.py
svcboot-2.0.7.dist-info/METADATA
svcboot-2.0.7.dist-info/WHEEL
svcboot-2.0.7.dist-info/entry_points.txt
svcboot-2.0.7.dist-info/top_level.txt
svcboot-2.0.7.dist-info/RECORD
