Metadata-Version: 2.1
Name: svcboot
Version: 2.0.7
Summary: svcboot离线打包
Home-page: UNKNOWN
Author: cuiyz
Author-email: cuiyz21@chinaunicom.cn
License: Apache License 2.0
Platform: UNKNOWN
Classifier: Development Status :: 4 - Beta
Classifier: Intended Audience :: Developers
Classifier: Intended Audience :: Science/Research
Classifier: Programming Language :: Python :: 3
Classifier: Programming Language :: Python :: 3.5
Classifier: Programming Language :: Python :: 3.6
Classifier: Programming Language :: Python :: 3.7
Classifier: Programming Language :: Python :: 3.8
Classifier: Programming Language :: Python :: 3.9
Classifier: License :: OSI Approved :: Apache Software License
Requires-Python: >=3.5
Requires-Dist: cython (==0.29.21)
Requires-Dist: python-consul (==1.1.0)
Requires-Dist: python-jwt (==3.2.6)
Requires-Dist: pyyaml (==5.3.1)
Requires-Dist: requests (==2.24.0)
Requires-Dist: tornado (==6.0.4)
